Pygeun/__init__.py
Pygeun/gradient_descent.py
Pygeun/levenberg_marquardt.py
Pygeun/newton_raphson.py
Pygeun-0.0.3.dist-info/METADATA
Pygeun-0.0.3.dist-info/WHEEL
Pygeun-0.0.3.dist-info/top_level.txt
Pygeun-0.0.3.dist-info/RECORD
